lifesim/__init__.py
lifesimpack_AviationSFO-1.3.0.dist-info/LICENSE
lifesimpack_AviationSFO-1.3.0.dist-info/METADATA
lifesimpack_AviationSFO-1.3.0.dist-info/WHEEL
lifesimpack_AviationSFO-1.3.0.dist-info/top_level.txt
lifesimpack_AviationSFO-1.3.0.dist-info/RECORD
