Metadata-Version: 2.1
Name: lifesimpack-AviationSFO
Version: 1.3.0
Summary: A life 'simulation' package created as a joke.
Home-page: https://github.com/AviationSFO/lifesimpack
Author: Steven Weinstein
Author-email: srw08sf@gmail.com
Project-URL: Bug Tracker, https://github.com/AviationSFO/lifesimpack/issues
Classifier: Programming Language :: Python :: 3
Classifier: License :: OSI Approved :: MIT License
Classifier: Operating System :: OS Independent
Requires-Python: >=3.6
License-File: LICENSE
